devcommit/__init__.py
devcommit/app/__init__.py
devcommit/app/ai_providers.py
devcommit/app/gemini_ai.py
devcommit/app/prompt.py
devcommit/main.py
devcommit/utils/__init__.py
devcommit/utils/git.py
devcommit/utils/logger.py
devcommit/utils/parser.py
devcommit-0.1.4.6.dist-info/METADATA
devcommit-0.1.4.6.dist-info/WHEEL
devcommit-0.1.4.6.dist-info/entry_points.txt
devcommit-0.1.4.6.dist-info/licenses/COPYING
devcommit-0.1.4.6.dist-info/RECORD
