Metadata-Version: 2.4
Name: devcommit
Version: 0.1.4.6
Summary: AI-powered git commit message generator
License: GNU GENERAL PUBLIC LICENSE
License-File: COPYING
Keywords: git,commit,ai,devcommit,commit-message,ai-commit,gemini,openai,ollama,groq
Author: Hordunlarmy
Author-email: Hordunlarmy@gmail.com
Requires-Python: >=3.10
Classifier: Development Status :: 4 - Beta
Classifier: Intended Audience :: Developers
Classifier: License :: OSI Approved :: GNU General Public License v3 (GPLv3)
Classifier: Programming Language :: Python :: 3
Classifier: Programming Language :: Python :: 3.10
Classifier: Programming Language :: Python :: 3.11
Classifier: Programming Language :: Python :: 3.12
Classifier: Topic :: Software Development :: Version Control :: Git
Classifier: Topic :: Software Development :: Libraries :: Python Modules
Requires-Dist: anthropic (>=0.25.0)
Requires-Dist: google-generativeai (>=0.7.1)
Requires-Dist: inquirerpy (>=0.3.4)
Requires-Dist: openai (>=1.0.0)
Requires-Dist: python-decouple (>=3.8)
Requires-Dist: requests (>=2.31.0)
Requires-Dist: rich (>=13.7.1)
Project-URL: Documentation, https://github.com/Hordunlarmy/DevCommit#readme
Project-URL: Homepage, https://github.com/Hordunlarmy/DevCommit
Project-URL: Issues, https://github.com/Hordunlarmy/DevCommit/issues
Project-URL: Repository, https://github.com/Hordunlarmy/DevCommit
